[
  {
    "team": "Argentina",
    "iso": "ar",
    "conf": "CONMEBOL",
    "elo": 2224,
    "squad_strength": 92.8,
    "n_big5": 20,
    "avg_age": 29.2,
    "reach_r16": 0.9102,
    "reach_qf": 0.7325,
    "reach_sf": 0.5047,
    "reach_final": 0.3251,
    "champion": 0.206
  },
  {
    "team": "Spain",
    "iso": "es",
    "conf": "UEFA",
    "elo": 2207,
    "squad_strength": 98.3,
    "n_big5": 26,
    "avg_age": 26.8,
    "reach_r16": 0.7866,
    "reach_qf": 0.5504,
    "reach_sf": 0.432,
    "reach_final": 0.2696,
    "champion": 0.1554
  },
  {
    "team": "France",
    "iso": "fr",
    "conf": "UEFA",
    "elo": 2196,
    "squad_strength": 95.2,
    "n_big5": 24,
    "avg_age": 27.1,
    "reach_r16": 1.0,
    "reach_qf": 0.7413,
    "reach_sf": 0.4819,
    "reach_final": 0.2879,
    "champion": 0.1528
  },
  {
    "team": "Brazil",
    "iso": "br",
    "conf": "CONMEBOL",
    "elo": 2115,
    "squad_strength": 86.3,
    "n_big5": 14,
    "avg_age": 29.4,
    "reach_r16": 1.0,
    "reach_qf": 0.6049,
    "reach_sf": 0.3353,
    "reach_final": 0.1659,
    "champion": 0.089
  },
  {
    "team": "England",
    "iso": "gb-eng",
    "conf": "UEFA",
    "elo": 2107,
    "squad_strength": 99.2,
    "n_big5": 25,
    "avg_age": 27.2,
    "reach_r16": 1.0,
    "reach_qf": 0.5749,
    "reach_sf": 0.2987,
    "reach_final": 0.1429,
    "champion": 0.0726
  },
  {
    "team": "Colombia",
    "iso": "co",
    "conf": "CONMEBOL",
    "elo": 2086,
    "squad_strength": 76.0,
    "n_big5": 9,
    "avg_age": 30.2,
    "reach_r16": 0.8646,
    "reach_qf": 0.5751,
    "reach_sf": 0.2687,
    "reach_final": 0.1412,
    "champion": 0.0714
  },
  {
    "team": "Morocco",
    "iso": "ma",
    "conf": "CAF",
    "elo": 2024,
    "squad_strength": 85.3,
    "n_big5": 15,
    "avg_age": 26.4,
    "reach_r16": 1.0,
    "reach_qf": 0.6443,
    "reach_sf": 0.2994,
    "reach_final": 0.1468,
    "champion": 0.0628
  },
  {
    "team": "Portugal",
    "iso": "pt",
    "conf": "UEFA",
    "elo": 2054,
    "squad_strength": 89.6,
    "n_big5": 17,
    "avg_age": 28.1,
    "reach_r16": 0.6282,
    "reach_qf": 0.2563,
    "reach_sf": 0.1645,
    "reach_final": 0.0792,
    "champion": 0.0338
  },
  {
    "team": "Mexico",
    "iso": "mx",
    "conf": "CONCACAF",
    "elo": 2045,
    "squad_strength": 63.0,
    "n_big5": 5,
    "avg_age": 28.0,
    "reach_r16": 1.0,
    "reach_qf": 0.4251,
    "reach_sf": 0.187,
    "reach_final": 0.0758,
    "champion": 0.0333
  },
  {
    "team": "Norway",
    "iso": "no",
    "conf": "UEFA",
    "elo": 2001,
    "squad_strength": 92.1,
    "n_big5": 19,
    "avg_age": 26.9,
    "reach_r16": 1.0,
    "reach_qf": 0.3951,
    "reach_sf": 0.1789,
    "reach_final": 0.0729,
    "champion": 0.0319
  },
  {
    "team": "Belgium",
    "iso": "be",
    "conf": "UEFA",
    "elo": 1961,
    "squad_strength": 91.8,
    "n_big5": 20,
    "avg_age": 27.7,
    "reach_r16": 1.0,
    "reach_qf": 0.5894,
    "reach_sf": 0.1987,
    "reach_final": 0.074,
    "champion": 0.0239
  },
  {
    "team": "Switzerland",
    "iso": "ch",
    "conf": "UEFA",
    "elo": 1983,
    "squad_strength": 93.9,
    "n_big5": 24,
    "avg_age": 28.4,
    "reach_r16": 0.5692,
    "reach_qf": 0.2384,
    "reach_sf": 0.082,
    "reach_final": 0.0312,
    "champion": 0.0117
  },
  {
    "team": "Canada",
    "iso": "ca",
    "conf": "CONCACAF",
    "elo": 1873,
    "squad_strength": 78.7,
    "n_big5": 11,
    "avg_age": 27.0,
    "reach_r16": 1.0,
    "reach_qf": 0.3557,
    "reach_sf": 0.112,
    "reach_final": 0.0383,
    "champion": 0.0114
  },
  {
    "team": "Paraguay",
    "iso": "py",
    "conf": "CONMEBOL",
    "elo": 1909,
    "squad_strength": 67.7,
    "n_big5": 5,
    "avg_age": 29.1,
    "reach_r16": 1.0,
    "reach_qf": 0.2587,
    "reach_sf": 0.1067,
    "reach_final": 0.0373,
    "champion": 0.0112
  },
  {
    "team": "United States",
    "iso": "us",
    "conf": "CONCACAF",
    "elo": 1878,
    "squad_strength": 84.2,
    "n_big5": 14,
    "avg_age": 27.0,
    "reach_r16": 1.0,
    "reach_qf": 0.4106,
    "reach_sf": 0.1066,
    "reach_final": 0.0319,
    "champion": 0.0081
  },
  {
    "team": "Australia",
    "iso": "au",
    "conf": "AFC",
    "elo": 1910,
    "squad_strength": 73.2,
    "n_big5": 9,
    "avg_age": 27.4,
    "reach_r16": 0.569,
    "reach_qf": 0.1461,
    "reach_sf": 0.0574,
    "reach_final": 0.0198,
    "champion": 0.0069
  },
  {
    "team": "Croatia",
    "iso": "hr",
    "conf": "UEFA",
    "elo": 1968,
    "squad_strength": 88.4,
    "n_big5": 18,
    "avg_age": 28.4,
    "reach_r16": 0.3718,
    "reach_qf": 0.1081,
    "reach_sf": 0.0566,
    "reach_final": 0.0206,
    "champion": 0.0063
  },
  {
    "team": "Austria",
    "iso": "at",
    "conf": "UEFA",
    "elo": 1903,
    "squad_strength": 87.0,
    "n_big5": 18,
    "avg_age": 28.7,
    "reach_r16": 0.2134,
    "reach_qf": 0.0851,
    "reach_sf": 0.0415,
    "reach_final": 0.0144,
    "champion": 0.0044
  },
  {
    "team": "Algeria",
    "iso": "dz",
    "conf": "CAF",
    "elo": 1890,
    "squad_strength": 80.0,
    "n_big5": 13,
    "avg_age": 26.9,
    "reach_r16": 0.4308,
    "reach_qf": 0.1548,
    "reach_sf": 0.0442,
    "reach_final": 0.0142,
    "champion": 0.0043
  },
  {
    "team": "Egypt",
    "iso": "eg",
    "conf": "CAF",
    "elo": 1858,
    "squad_strength": 57.6,
    "n_big5": 5,
    "avg_age": 29.1,
    "reach_r16": 0.431,
    "reach_qf": 0.0944,
    "reach_sf": 0.0328,
    "reach_final": 0.0093,
    "champion": 0.0026
  },
  {
    "team": "Ghana",
    "iso": "gh",
    "conf": "CAF",
    "elo": 1687,
    "squad_strength": 87.2,
    "n_big5": 17,
    "avg_age": 27.0,
    "reach_r16": 0.1354,
    "reach_qf": 0.0318,
    "reach_sf": 0.0045,
    "reach_final": 0.0006,
    "champion": 0.0001
  },
  {
    "team": "Cape Verde",
    "iso": "cv",
    "conf": "CAF",
    "elo": 1701,
    "squad_strength": 59.2,
    "n_big5": 1,
    "avg_age": 29.7,
    "reach_r16": 0.0898,
    "reach_qf": 0.027,
    "reach_sf": 0.0056,
    "reach_final": 0.001,
    "champion": 0.0001
  }
]